wpiformat/__init__.py
wpiformat/__main__.py
wpiformat/bracecomment.py
wpiformat/cidentlist.py
wpiformat/clangformat.py
wpiformat/clangtidy.py
wpiformat/cmakeformat.py
wpiformat/config.py
wpiformat/eofnewline.py
wpiformat/gtestname.py
wpiformat/includeguard.py
wpiformat/javaclass.py
wpiformat/jni.py
wpiformat/licenseupdate.py
wpiformat/lint.py
wpiformat/pyformat.py
wpiformat/task.py
wpiformat/usingdeclaration.py
wpiformat/usingnamespacestd.py
wpiformat/version.py
wpiformat/whitespace.py
wpiformat-2025.79.dist-info/licenses/LICENSE.txt
wpiformat-2025.79.dist-info/METADATA
wpiformat-2025.79.dist-info/WHEEL
wpiformat-2025.79.dist-info/entry_points.txt
wpiformat-2025.79.dist-info/top_level.txt
wpiformat-2025.79.dist-info/RECORD
