Metadata-Version: 2.4
Name: wpiformat
Version: 2025.79
Summary: Linters and formatters for ensuring WPILib's source code conforms to its style guide
Maintainer-email: Tyler Veness <calcmogul@gmail.com>
License-Expression: BSD-3-Clause
Project-URL: Homepage, https://github.com/wpilibsuite/styleguide
Classifier: Development Status :: 5 - Production/Stable
Classifier: Intended Audience :: Developers
Classifier: Intended Audience :: Education
Classifier: Operating System :: OS Independent
Classifier: Topic :: Scientific/Engineering
Classifier: Programming Language :: Python :: 3
Requires-Python: >=3.11
License-File: LICENSE.txt
Requires-Dist: autoflake==2.3.1
Requires-Dist: black==25.9.0
Requires-Dist: clang-format==21.1.2
Requires-Dist: clang-tidy==21.1.1
Requires-Dist: cpplint==2.0.2
Requires-Dist: gersemi==0.22.3
Requires-Dist: isort==7.0.0
Dynamic: license-file
